COPYING
COPYING.LESSER
ffms2/__init__.py
ffms2/__main__.py
ffms2/av_log.py
ffms2/console_mode.py
ffms2/enums.py
ffms2/get_library.py
ffms2/libffms2.py
ffms2/test.py
ffms2/data/ffmsinfo.cpp
ffms2/data/morning rescue.mkv
ffms2-0.4.5.5.data/data/Scripts/ffms2.dll
ffms2-0.4.5.5.data/data/Scripts/ffms2.lib
ffms2-0.4.5.5.data/data/Scripts/ffmsindex.exe
ffms2-0.4.5.5.dist-info/COPYING
ffms2-0.4.5.5.dist-info/COPYING.LESSER
ffms2-0.4.5.5.dist-info/METADATA
ffms2-0.4.5.5.dist-info/WHEEL
ffms2-0.4.5.5.dist-info/top_level.txt
ffms2-0.4.5.5.dist-info/RECORD
