Metadata-Version: 2.1
Name: ffms2
Version: 0.4.5.5
Summary: Bindings for FFmpegSource
Home-page: https://github.com/bubblesub/pyffms2
Author: spirit
Author-email: hiddenspirit@gmail.com
License: UNKNOWN
Platform: UNKNOWN
Classifier: Development Status :: 3 - Alpha
Classifier: License :: OSI Approved :: GNU Lesser General Public License v3 or later (LGPLv3+)
Classifier: Programming Language :: Python :: 3
Classifier: Programming Language :: Python :: 3.7
Classifier: Programming Language :: Python :: 3.8
Classifier: Programming Language :: Python :: 3.9
Requires-Python: >=3.7
Requires-Dist: numpy
